panda_utils/__init__.py
panda_utils/__main__.py
panda_utils/util.py
panda_utils/assetpipeline/__init__.py
panda_utils/assetpipeline/__main__.py
panda_utils/assetpipeline/blender.py
panda_utils/assetpipeline/commons.py
panda_utils/assetpipeline/composer.py
panda_utils/assetpipeline/imports.py
panda_utils/assetpipeline/misc.py
panda_utils/assetpipeline/models.py
panda_utils/assetpipeline/target_parser.py
panda_utils/assetpipeline/textures.py
panda_utils/blender/__init__.py
panda_utils/blender/export_glb.py
panda_utils/blender/export_with_yabee.py
panda_utils/blender/import_model.py
panda_utils/blender/patch_paths.py
panda_utils/eggtree/__init__.py
panda_utils/eggtree/eggparse.py
panda_utils/eggtree/operations.py
panda_utils/tools/__init__.py
panda_utils/tools/animconvert.py
panda_utils/tools/convert.py
panda_utils/tools/downscale.py
panda_utils/tools/palettize.py
panda_utils/tools/toontown.py
panda_utils-1.6.5.dist-info/licenses/LICENSE
panda_utils-1.6.5.dist-info/METADATA
panda_utils-1.6.5.dist-info/WHEEL
panda_utils-1.6.5.dist-info/top_level.txt
panda_utils-1.6.5.dist-info/RECORD
