Metadata-Version: 2.4
Name: panda_utils
Version: 1.6.5
Summary: PandaUtils includes multiple tools for basic Panda3D automation
Author-email: "Toontown: Event Horizon" <development@toontowneventhorizon.com>
Project-URL: homepage, https://github.com/toontown-event-horizon/panda-utils
Project-URL: bugtracker, https://github.com/toontown-event-horizon/panda-utils/issues
Classifier: Programming Language :: Python :: 3.9
Classifier: License :: OSI Approved :: MIT License
Classifier: Operating System :: OS Independent
Requires-Python: >=3.9
License-File: LICENSE
Provides-Extra: imagery
Requires-Dist: Pillow>=9.0; extra == "imagery"
Provides-Extra: autopath
Requires-Dist: panda3d!=1.10.13.*,~=1.10; extra == "autopath"
Provides-Extra: runnable
Requires-Dist: platformdirs~=3.5; extra == "runnable"
Provides-Extra: pipeline
Requires-Dist: pyyaml~=6.0; extra == "pipeline"
Requires-Dist: numpy~=1.24; extra == "pipeline"
Requires-Dist: panda3d-blend2bam!=1.0.0; extra == "pipeline"
Requires-Dist: panda3d!=1.10.13.*,~=1.10; extra == "pipeline"
Provides-Extra: composer
Requires-Dist: panda_utils[pipeline]; extra == "composer"
Requires-Dist: doit; extra == "composer"
Requires-Dist: pydantic; extra == "composer"
Provides-Extra: everything
Requires-Dist: panda_utils[imagery]; extra == "everything"
Requires-Dist: panda_utils[autopath]; extra == "everything"
Requires-Dist: panda_utils[runnable]; extra == "everything"
Requires-Dist: panda_utils[composer]; extra == "everything"
Dynamic: license-file
